Workbook

Sheet Center_Cities
A1: City | B1: State | C1: LAT | D1: LON
A2: Birmingham | B2: AL | C2: 33.518661 | D2: -86.810325
A3: Anchorage | B3: AK | C3: 61.217041 | D3: -149.89082
A4: Phoenix | B4: AZ | C4: 33.455476 | D4: -112.07028
A5: Tucson | B5: AZ | C5: 32.220172 | D5: -110.97405
A6: Los Angeles | B6: CA | C6: 34.044218 | D6: -118.24418
A7: Oakland | B7: CA | C7: 37.804418 | D7: -122.2712
A8: San Diego | B8: CA | C8: 32.714678 | D8: -117.16242
A9: San Francisco | B9: CA | C9: 37.779607 | D9: -122.41765
A10: Denver | B10: CO | C10: 39.74788 | D10: -105.00004
A11: Washington DC | B11: DC | C11: 38.905295 | D11: -77.038399
A12: Jacksonville | B12: FL | C12: 30.327864 | D12: -81.654782
A13: Miami | B13: FL | C13: 25.77539 | D13: -80.192692
... A47: Milwaukee | B47: WI | C47: 43.038972 | D47: -87.903837

Sheet Cities
A1: City | B1: State | C1: State_Adj | D1: LAT | E1: LON
A2: ='Raw List'!J8 -> Birmingham | B2: ='Raw List'!M8 -> AL | C2: =SUBSTITUTE(B2," ","") -> AL | D2: ='Raw List'!N8 -> 33.57 | E2: =-'Raw List'!O8 -> -86.75
A3: ='Raw List'!J28 -> Anchorage | B3: ='Raw List'!M28 -> AK | C3: =SUBSTITUTE(B3," ","") -> AK | D3: ='Raw List'!N28 -> 61.17 | E3: =-'Raw List'!O28 -> -150.02
A4: ='Raw List'!J74 -> Juneau | B4: ='Raw List'!M74 -> AK | C4: =SUBSTITUTE(B4," ","") -> AK | D4: ='Raw List'!N74 -> 58.37 | E4: =-'Raw List'!O74 -> -134.58
A5: ='Raw List'!J146 -> Phoenix | B5: ='Raw List'!M146 -> AZ | C5: =SUBSTITUTE(B5," ","") -> AZ | D5: ='Raw List'!N146 -> 33.43 | E5: =-'Raw List'!O146 -> -112.02
A6: ='Raw List'!J152 -> Tucson | B6: ='Raw List'!M152 -> AZ | C6: =SUBSTITUTE(B6," ","") -> AZ | D6: ='Raw List'!N152 -> 32.12 | E6: =-'Raw List'!O152 -> -110.93
A7: ='Raw List'!J170 -> Little Rock | B7: ='Raw List'!M170 -> AR | C7: =SUBSTITUTE(B7," ","") -> AR | D7: ='Raw List'!N170 -> 35.22 | E7: =-'Raw List'!O170 -> -92.38
A8: ='Raw List'!J191 -> Burbank | B8: ='Raw List'!M191 -> CA | C8: =SUBSTITUTE(B8," ","") -> CA | D8: ='Raw List'!N191 -> 34.2 | E8: =-'Raw List'!O191 -> -118.37
A9: ='Raw List'!J221 -> Long Beach | B9: ='Raw List'!M221 -> CA | C9: =SUBSTITUTE(B9," ","") -> CA | D9: ='Raw List'!N221 -> 33.82 | E9: =-'Raw List'!O221 -> -118.15
A10: ='Raw List'!J223 -> Los Angeles | B10: ='Raw List'!M223 -> CA | C10: =SUBSTITUTE(B10," ","") -> CA | D10: ='Raw List'!N223 -> 33.93 | E10: =-'Raw List'!O223 -> -118.4
A11: ='Raw List'!J242 -> Oakland | B11: ='Raw List'!M242 -> CA | C11: =SUBSTITUTE(B11," ","") -> CA | D11: ='Raw List'!N242 -> 37.73 | E11: =-'Raw List'!O242 -> -122.22
A12: ='Raw List'!J264 -> San Diego | B12: ='Raw List'!M264 -> CA | C12: =SUBSTITUTE(B12," ","") -> CA | D12: ='Raw List'!N264 -> 32.82 | E12: =-'Raw List'!O264 -> -117.13
A13: ='Raw List'!J269 -> San Francisco | B13: ='Raw List'!M269 -> CA | C13: =SUBSTITUTE(B13," ","") -> CA | D13: ='Raw List'!N269 -> 37.75 | E13: =-'Raw List'!O269 -> -122.68
A14: ='Raw List'!J271 -> San Jose | B14: ='Raw List'!M271 -> CA | C14: =SUBSTITUTE(B14," ","") -> CA | D14: ='Raw List'!N271 -> 37.37 | E14: =-'Raw List'!O271 -> -121.92
A15: ='Raw List'!J311 -> Denver | B15: ='Raw List'!M311 -> CO | C15: =SUBSTITUTE(B15," ","") -> CO | D15: ='Raw List'!N311 -> 39.75 | E15: =-'Raw List'!O311 -> -104.87
A16: ='Raw List'!J338 -> Bridgeport | B16: ='Raw List'!M338 -> CT | C16: =SUBSTITUTE(B16," ","") -> CT | D16: ='Raw List'!N338 -> 41.17 | E16: =-'Raw List'!O338 -> -73.13
A17: ='Raw List'!J341 -> Hartford | B17: ='Raw List'!M341 -> CT | C17: =SUBSTITUTE(B17," ","") -> CT | D17: ='Raw List'!N341 -> 41.73 | E17: =-'Raw List'!O341 -> -72.65
A18: ='Raw List'!J357 -> Washington | B18: ='Raw List'!M357 -> DC | C18: =SUBSTITUTE(B18," ","") -> DC | D18: ='Raw List'!N357 -> 38.85 | E18: =-'Raw List'!O357 -> -77.04
A19: ='Raw List'!J374 -> Ft Lauderdale | B19: ='Raw List'!M374 -> FL | C19: =SUBSTITUTE(B19," ","") -> FL | D19: ='Raw List'!N374 -> 26.07 | E19: =-'Raw List'!O374 -> -80.15
A20: ='Raw List'!J381 -> Jacksonville | B20: ='Raw List'!M381 -> FL | C20: =SUBSTITUTE(B20," ","") -> FL | D20: ='Raw List'!N381 -> 30.23 | E20: =-'Raw List'!O381 -> -81.68
A21: Miami | B21: ='Raw List'!M389 -> FL | C21: =SUBSTITUTE(B21," ","") -> FL | D21: ='Raw List'!N389 -> 25.82 | E21: =-'Raw List'!O389 -> -80.28
A22: ='Raw List'!J394 -> Orlando | B22: ='Raw List'!M394 -> FL | C22: =SUBSTITUTE(B22," ","") -> FL | D22: ='Raw List'!N394 -> 28.43 | E22: =-'Raw List'!O394 -> -81.32
A23: Tampa | B23: ='Raw List'!M405 -> FL | C23: =SUBSTITUTE(B23," ","") -> FL | D23: ='Raw List'!N405 -> 27.97 | E23: =-'Raw List'!O405 -> -82.53
A24: ='Raw List'!J418 -> Atlanta | B24: ='Raw List'!M418 -> GA | C24: =SUBSTITUTE(B24," ","") -> GA | D24: ='Raw List'!N418 -> 33.65 | E24: =-'Raw List'!O418 -> -84.42
A25: Honolulu | B25: ='Raw List'!M445 -> HI | C25: =SUBSTITUTE(B25," ","") -> HI | D25: ='Raw List'!N445 -> 21.35 | E25: =-'Raw List'!O445 -> -157.93
A26: ='Raw List'!J460 -> Boise | B26: ='Raw List'!M460 -> ID | C26: =SUBSTITUTE(B26," ","") -> ID | D26: ='Raw List'!N460 -> 43.57 | E26: =-'Raw List'!O460 -> -116.22
A27: ='Raw List'!J492 -> Chicago | B27: ='Raw List'!M492 -> IL | C27: =SUBSTITUTE(B27," ","") -> IL | D27: ='Raw List'!N492 -> 41.9 | E27: =-'Raw List'!O492 -> -87.65
A28: ='Raw List'!J529 -> Indianapolis | B28: ='Raw List'!M529 -> IN | C28: =SUBSTITUTE(B28," ","") -> IN | D28: ='Raw List'!N529 -> 39.73 | E28: =-'Raw List'!O529 -> -86.27
A29: ='Raw List'!J539 -> Des Moines | B29: ='Raw List'!M539 -> IA | C29: =SUBSTITUTE(B29," ","") -> IA | D29: ='Raw List'!N539 -> 41.53 | E29: =-'Raw List'!O539 -> -93.65
A30: ='Raw List'!J586 -> Louisville | B30: ='Raw List'!M586 -> KY | C30: =SUBSTITUTE(B30," ","") -> KY | D30: ='Raw List'!N586 -> 38.18 | E30: =-'Raw List'!O586 -> -85.73
A31: ='Raw List'!J595 -> Baton Rouge | B31: ='Raw List'!M595 -> LA | C31: =SUBSTITUTE(B31," ","") -> LA | D31: ='Raw List'!N595 -> 30.53 | E31: =-'Raw List'!O595 -> -91.15
A32: ='Raw List'!J614 -> New Orleans | B32: ='Raw List'!M614 -> LA | C32: =SUBSTITUTE(B32," ","") -> LA | D32: ='Raw List'!N614 -> 29.98 | E32: =-'Raw List'!O614 -> -90.25
A33: ='Raw List'!J633 -> Portland | B33: ='Raw List'!M633 -> ME | C33: =SUBSTITUTE(B33," ","") -> ME | D33: ='Raw List'!N633 -> 43.65 | E33: =-'Raw List'!O633 -> -70.32
A34: ='Raw List'!J643 -> Baltimore | B34: ='Raw List'!M643 -> MD | C34: =SUBSTITUTE(B34," ","") -> MD | D34: ='Raw List'!N643 -> 39.33 | E34: =-'Raw List'!O643 -> -76.42
A35: ='Raw List'!J655 -> Boston | B35: ='Raw List'!M655 -> MA | C35: =SUBSTITUTE(B35," ","") -> MA | D35: ='Raw List'!N655 -> 42.37 | E35: =-'Raw List'!O655 -> -71.03
A36: ='Raw List'!J674 -> Alpena | B36: ='Raw List'!M674 -> MI | C36: =SUBSTITUTE(B36," ","") -> MI | D36: ='Raw List'!N674 -> 45.07 | E36: =-'Raw List'!O674 -> -83.57
A37: ='Raw List'!J675 -> Ann Arbor | B37: ='Raw List'!M675 -> MI | C37: =SUBSTITUTE(B37," ","") -> MI | D37: ='Raw List'!N675 -> 42.22 | E37: =-'Raw List'!O675 -> -83.75
A38: ='Raw List'!J681 -> Detroit | B38: ='Raw List'!M681 -> MI | C38: =SUBSTITUTE(B38," ","") -> MI | D38: ='Raw List'!N681 -> 42.42 | E38: =-'Raw List'!O681 -> -83.02
A39: ='Raw List'!J728 -> Minneapolis | B39: ='Raw List'!M728 -> MN | C39: =SUBSTITUTE(B39," ","") -> MN | D39: ='Raw List'!N728 -> 44.88 | E39: =-'Raw List'!O728 -> -93.22
A40: ='Raw List'!J765 -> Kansas City | B40: ='Raw List'!M765 -> MO | C40: =SUBSTITUTE(B40," ","") -> MO | D40: ='Raw List'!N765 -> 39.32 | E40: =-'Raw List'!O765 -> -94.72
A41: ='Raw List'!J775 -> St Louis | B41: ='Raw List'!M775 -> MO | C41: =SUBSTITUTE(B41," ","") -> MO | D41: ='Raw List'!N775 -> 38.75 | E41: =-'Raw List'!O775 -> -90.37
A42: ='Raw List'!J784 -> Billings | B42: ='Raw List'!M784 -> MT | C42: =SUBSTITUTE(B42," ","") -> MT | D42: ='Raw List'!N784 -> 45.8 | E42: =-'Raw List'!O784 -> -108.53
A43: ='Raw List'!J785 -> Bozeman | B43: ='Raw List'!M785 -> MT | C43: =SUBSTITUTE(B43," ","") -> MT | D43: ='Raw List'!N785 -> 45.78 | E43: =-'Raw List'!O785 -> -111.15
A44: Omaha | B44: ='Raw List'!M835 -> NE | C44: =SUBSTITUTE(B44," ","") -> NE | D44: ='Raw List'!N835 -> 41.3 | E44: =-'Raw List'!O835 -> -95.9
A45: ='Raw List'!J854 -> Las Vegas | B45: ='Raw List'!M854 -> NV | C45: =SUBSTITUTE(B45," ","") -> NV | D45: ='Raw List'!N854 -> 36.08 | E45: =-'Raw List'!O854 -> -115.17
A46: ='Raw List'!J859 -> Reno | B46: ='Raw List'!M859 -> NV | C46: =SUBSTITUTE(B46," ","") -> NV | D46: ='Raw List'!N859 -> 39.5 | E46: =-'Raw List'!O859 -> -119.78
A47: ='Raw List'!J894 -> Albuquerque | B47: ='Raw List'!M894 -> NM | C47: =SUBSTITUTE(B47," ","") -> NM | D47: ='Raw List'!N894 -> 35.05 | E47: =-'Raw List'!O894 -> -106.6
A48: New York | B48: ='Raw List'!M940 -> NY | C48: =SUBSTITUTE(B48," ","") -> NY | D48: ='Raw List'!N940 -> 40.77 | E48: =-'Raw List'!O940 -> -73.9
A49: ='Raw List'!J948 -> Rochester | B49: ='Raw List'!M948 -> NY | C49: =SUBSTITUTE(B49," ","") -> NY | D49: ='Raw List'!N948 -> 43.12 | E49: =-'Raw List'!O948 -> -77.67
A50: ='Raw List'!J951 -> Syracuse | B50: ='Raw List'!M951 -> NY | C50: =SUBSTITUTE(B50," ","") -> NY | D50: ='Raw List'!N951 -> 43.12 | E50: =-'Raw List'!O951 -> -76.12
A51: ='Raw List'!J961 -> Charlotte | B51: ='Raw List'!M961 -> NC | C51: =SUBSTITUTE(B51," ","") -> NC | D51: ='Raw List'!N961 -> 35.22 | E51: =-'Raw List'!O961 -> -80.93
A52: ='Raw List'!J978 -> Raleigh-Durham | B52: ='Raw List'!M978 -> NC | C52: =SUBSTITUTE(B52," ","") -> NC | D52: ='Raw List'!N978 -> 35.87 | E52: =-'Raw List'!O978 -> -78.78
A53: ='Raw List'!J1005 -> Cincinnati | B53: ='Raw List'!M1005 -> OH | C53: =SUBSTITUTE(B53," ","") -> OH | D53: ='Raw List'!N1005 -> 39.05 | E53: =-'Raw List'!O1005 -> -84.67
A54: ='Raw List'!J1007 -> Cleveland | B54: ='Raw List'!M1007 -> OH | C54: =SUBSTITUTE(B54," ","") -> OH | D54: ='Raw List'!N1007 -> 41.52 | E54: =-'Raw List'!O1007 -> -81.68
A55: Columbus | B55: ='Raw List'!M1011 -> OH | C55: =SUBSTITUTE(B55," ","") -> OH | D55: ='Raw List'!N1011 -> 40.08 | E55: =-'Raw List'!O1011 -> -83.07
A56: Oklahoma City | B56: ='Raw List'!M1036 -> OK | C56: =SUBSTITUTE(B56," ","") -> OK | D56: ='Raw List'!N1036 -> 35.53 | E56: =-'Raw List'!O1036 -> -97.65
A57: ='Raw List'!J1041 -> Tulsa | B57: ='Raw List'!M1041 -> OK | C57: =SUBSTITUTE(B57," ","") -> OK | D57: ='Raw List'!N1041 -> 36.2 | E57: =-'Raw List'!O1041 -> -95.9
A58: ='Raw List'!J1065 -> Portland | B58: ='Raw List'!M1065 -> OR | C58: =SUBSTITUTE(B58," ","") -> OR | D58: ='Raw List'!N1065 -> 45.6 | E58: =-'Raw List'!O1065 -> -122.6
A59: ='Raw List'!J1084 -> Harrisburg | B59: ='Raw List'!M1084 -> PA | C59: =SUBSTITUTE(B59," ","") -> PA | D59: ='Raw List'!N1084 -> 40.37 | E59: =-'Raw List'!O1084 -> -77.42
A60: ='Raw List'!J1091 -> Philadelphia | B60: ='Raw List'!M1091 -> PA | C60: =SUBSTITUTE(B60," ","") -> PA | D60: ='Raw List'!N1091 -> 39.88 | E60: =-'Raw List'!O1091 -> -75.25
A61: ='Raw List'!J1093 -> Pittsburgh | B61: ='Raw List'!M1093 -> PA | C61: =SUBSTITUTE(B61," ","") -> PA | D61: ='Raw List'!N1093 -> 40.35 | E61: =-'Raw List'!O1093 -> -79.93
A62: ='Raw List'!J1106 -> Providence | B62: ='Raw List'!M1106 -> RI | C62: =SUBSTITUTE(B62," ","") -> RI | D62: ='Raw List'!N1106 -> 41.73 | E62: =-'Raw List'!O1106 -> -71.43
A63: ='Raw List'!J1153 -> Knoxville | B63: ='Raw List'!M1153 -> TN | C63: =SUBSTITUTE(B63," ","") -> TN | D63: ='Raw List'!N1153 -> 35.82 | E63: =-'Raw List'!O1153 -> -83.98
A64: Memphis | B64: ='Raw List'!M1154 -> TN | C64: =SUBSTITUTE(B64," ","") -> TN | D64: ='Raw List'!N1154 -> 35.05 | E64: =-'Raw List'!O1154 -> -90
A65: ='Raw List'!J1157 -> Nashville | B65: ='Raw List'!M1157 -> TN | C65: =SUBSTITUTE(B65," ","") -> TN | D65: ='Raw List'!N1157 -> 36.12 | E65: =-'Raw List'!O1157 -> -86.68
A66: ='Raw List'!J1165 -> Austin | B66: ='Raw List'!M1165 -> TX | C66: =SUBSTITUTE(B66," ","") -> TX | D66: ='Raw List'!N1165 -> 30.3 | E66: =-'Raw List'!O1165 -> -97.7
A67: ='Raw List'!J1182 -> Dallas/FW | B67: ='Raw List'!M1182 -> TX | C67: =SUBSTITUTE(B67," ","") -> TX | D67: ='Raw List'!N1182 -> 32.9 | E67: =-'Raw List'!O1182 -> -97.03
A68: ='Raw List'!J1197 -> Houston | B68: ='Raw List'!M1197 -> TX | C68: =SUBSTITUTE(B68," ","") -> TX | D68: ='Raw List'!N1197 -> 29.97 | E68: =-'Raw List'!O1197 -> -95.35
A69: ='Raw List'!J1221 -> San Antonio | B69: ='Raw List'!M1221 -> TX | C69: =SUBSTITUTE(B69," ","") -> TX | D69: ='Raw List'!N1221 -> 29.53 | E69: =-'Raw List'!O1221 -> -98.47
A70: ='Raw List'!J1253 -> Salt Lake | B70: UT | C70: =SUBSTITUTE(B70," ","") -> UT | D70: ='Raw List'!N1253 -> 40.78 | E70: =-'Raw List'!O1253 -> -111.97
A71: ='Raw List'!J1282 -> Richmond | B71: ='Raw List'!M1282 -> VA | C71: =SUBSTITUTE(B71," ","") -> VA | D71: ='Raw List'!N1282 -> 37.5 | E71: =-'Raw List'!O1282 -> -77.33
A72: ='Raw List'!J1290 -> Bellingham | B72: ='Raw List'!M1290 -> WA | C72: =SUBSTITUTE(B72," ","") -> WA | D72: ='Raw List'!N1290 -> 48.8 | E72: =-'Raw List'!O1290 -> -122.53
A73: ='Raw List'!J1311 -> Seattle | B73: ='Raw List'!M1311 -> WA | C73: =SUBSTITUTE(B73," ","") -> WA | D73: ='Raw List'!N1311 -> 47.45 | E73: =-'Raw List'!O1311 -> -122.3
A74: ='Raw List'!J1334 -> Morgantown | B74: ='Raw List'!M1334 -> WV | C74: =SUBSTITUTE(B74," ","") -> WV | D74: ='Raw List'!N1334 -> 39.65 | E74: =-'Raw List'!O1334 -> -79.92
A75: ='Raw List'!J1350 -> Milwaukee | B75: ='Raw List'!M1350 -> WI | C75: =SUBSTITUTE(B75," ","") -> WI | D75: ='Raw List'!N1350 -> 43.12 | E75: =-'Raw List'!O1350 -> -88.05

Sheet Raw List
A1: ID | B1: LAT | C1: LON | D1: Location
A2: https://www.w3.org/2003/01/geo/test/ustowns/latlong.htm
A3: Alabama
J5: City | K5: State | M5: State Adj. | N5: LAT | O5: LON
A6: [ANB] | B6: 33.58 | C6: 85.85 | D6: Anniston,AL | H6: Anniston,AL | J6: =LEFT(H6,LEN(H6)-5) -> Anniston | K6: =RIGHT(H6,4) -> AL | L6: =LEFT(K6,LEN(K6)-1) -> AL | M6: =SUBSTITUTE(L6,",","") -> AL | N6: =B6 -> 33.58 | O6: =C6 -> 85.85
A7: [AUO] | B7: 32.67 | C7: 85.44 | D7: Auburn,AL | H7: Auburn,AL | J7: =LEFT(H7,LEN(H7)-5) -> Auburn | K7: =RIGHT(H7,4) -> AL | L7: =LEFT(K7,LEN(K7)-1) -> AL | M7: =SUBSTITUTE(L7,",","") -> AL | N7: =B7 -> 32.67 | O7: =C7 -> 85.44
A8: [BHM] | B8: 33.57 | C8: 86.75 | D8: Birmingham,AL | H8: Birmingham,AL | J8: =LEFT(H8,LEN(H8)-5) -> Birmingham | K8: =RIGHT(H8,4) -> AL | L8: =LEFT(K8,LEN(K8)-1) -> AL | M8: =SUBSTITUTE(L8,",","") -> AL | N8: =B8 -> 33.57 | O8: =C8 -> 86.75
A9: [CKL] | B9: 32.9 | C9: 87.25 | D9: Centreville,AL | H9: Centreville,AL | J9: =LEFT(H9,LEN(H9)-5) -> Centreville | K9: =RIGHT(H9,4) -> AL | L9: =LEFT(K9,LEN(K9)-1) -> AL | M9: =SUBSTITUTE(L9,",","") -> AL | N9: =B9 -> 32.9 | O9: =C9 -> 87.25
A10: [DHN] | B10: 31.32 | C10: 85.45 | D10: Dothan,AL | H10: Dothan,AL | J10: =LEFT(H10,LEN(H10)-5) -> Dothan | K10: =RIGHT(H10,4) -> AL | L10: =LEFT(K10,LEN(K10)-1) -> AL | M10: =SUBSTITUTE(L10,",","") -> AL | N10: =B10 -> 31.32 | O10: =C10 -> 85.45
A11: [OZR] | B11: 31.28 | C11: 85.72 | D11: Fort | E11: Rucker,AL | H11: Fort Rucker,AL | J11: =LEFT(H11,LEN(H11)-5) -> Fort Rucke | K11: =RIGHT(H11,4) -> ,AL | L11: =LEFT(K11,LEN(K11)-1) -> ,AL | M11: =SUBSTITUTE(L11,",","") -> AL | N11: =B11 -> 31.28 | O11: =C11 -> 85.72
A12: [GAD] | B12: 33.97 | C12: 86.09 | D12: Gadsden,AL | H12: Gadsden,AL | J12: =LEFT(H12,LEN(H12)-5) -> Gadsden | K12: =RIGHT(H12,4) -> AL | L12: =LEFT(K12,LEN(K12)-1) -> AL | M12: =SUBSTITUTE(L12,",","") -> AL | N12: =B12 -> 33.97 | O12: =C12 -> 86.09
A13: [HSV] | B13: 34.65 | C13: 86.77 | D13: Huntsville,AL | H13: Huntsville,AL | J13: =LEFT(H13,LEN(H13)-5) -> Huntsville | K13: =RIGHT(H13,4) -> AL | L13: =LEFT(K13,LEN(K13)-1) -> AL | M13: =SUBSTITUTE(L13,",","") -> AL | N13: =B13 -> 34.65 | O13: =C13 -> 86.77
A14: [MXF] | B14: 32.38 | C14: 86.37 | D14: Maxwell | E14: AFB,AL | H14: Maxwell AFB,AL | J14: =LEFT(H14,LEN(H14)-5) -> Maxwell AF | K14: =RIGHT(H14,4) -> ,AL | L14: =LEFT(K14,LEN(K14)-1) -> ,AL | M14: =SUBSTITUTE(L14,",","") -> AL | N14: =B14 -> 32.38 | O14: =C14 -> 86.37
A15: [MOB] | B15: 30.68 | C15: 88.25 | D15: Mobile,AL | H15: Mobile,AL | J15: =LEFT(H15,LEN(H15)-5) -> Mobile | K15: =RIGHT(H15,4) -> AL | L15: =LEFT(K15,LEN(K15)-1) -> AL | M15: =SUBSTITUTE(L15,",","") -> AL | N15: =B15 -> 30.68 | O15: =C15 -> 88.25
A16: [BFM] | B16: 30.63 | C16: 88.07 | D16: Mobile | E16: Aeros,AL | H16: Mobile Aeros,AL | J16: =LEFT(H16,LEN(H16)-5) -> Mobile Aero | K16: =RIGHT(H16,4) -> ,AL | L16: =LEFT(K16,LEN(K16)-1) -> ,AL | M16: =SUBSTITUTE(L16,",","") -> AL | N16: =B16 -> 30.63 | O16: =C16 -> 88.07
A17: [MGM] | B17: 32.3 | C17: 86.4 | D17: Montgomery,AL | H17: Montgomery,AL | J17: =LEFT(H17,LEN(H17)-5) -> Montgomery | K17: =RIGHT(H17,4) -> AL | L17: =LEFT(K17,LEN(K17)-1) -> AL | M17: =SUBSTITUTE(L17,",","") -> AL | N17: =B17 -> 32.3 | O17: =C17 -> 86.4
A18: [MSL] | B18: 34.75 | C18: 87.62 | D18: Muscle | E18: Shoal,AL | H18: Muscle Shoal,AL | J18: =LEFT(H18,LEN(H18)-5) -> Muscle Shoa | K18: =RIGHT(H18,4) -> ,AL | L18: =LEFT(K18,LEN(K18)-1) -> ,AL | M18: =SUBSTITUTE(L18,",","") -> AL | N18: =B18 -> 34.75 | O18: =C18 -> 87.62
A19: [SEM] | B19: 32.34 | C19: 86.99 | D19: Selma,AL | H19: Selma,AL | J19: =LEFT(H19,LEN(H19)-5) -> Selma | K19: =RIGHT(H19,4) -> AL | L19: =LEFT(K19,LEN(K19)-1) -> AL | M19: =SUBSTITUTE(L19,",","") -> AL | N19: =B19 -> 32.34 | O19: =C19 -> 86.99
A20: [TOI] | B20: 31.87 | C20: 86.02 | D20: Troy,AL | H20: Troy,AL | J20: =LEFT(H20,LEN(H20)-5) -> Troy | K20: =RIGHT(H20,4) -> AL | L20: =LEFT(K20,LEN(K20)-1) -> AL | M20: =SUBSTITUTE(L20,",","") -> AL | N20: =B20 -> 31.87 | O20: =C20 -> 86.02
A21: [TCL] | B21: 33.23 | C21: 87.62 | D21: Tuscaloosa,AL | H21: Tuscaloosa,AL | J21: =LEFT(H21,LEN(H21)-5) -> Tuscaloosa | K21: =RIGHT(H21,4) -> AL | L21: =LEFT(K21,LEN(K21)-1) -> AL | M21: =SUBSTITUTE(L21,",","") -> AL | N21: =B21 -> 33.23 | O21: =C21 -> 87.62
A23: Alaska
A26: [ADK] | B26: 51.88 | C26: 176.65 | D26: Adak,AK | H26: Adak,AK | J26: =LEFT(H26,LEN(H26)-5) -> Adak | K26: =RIGHT(H26,4) -> AK | L26: =LEFT(K26,LEN(K26)-1) -> AK | M26: =SUBSTITUTE(L26,",","") -> AK | N26: =B26 -> 51.88 | O26: =C26 -> 176.65
A27: [Z60] | B27: 67.1 | C27: 157.85 | D27: Ambler,AK | H27: Ambler,AK | J27: =LEFT(H27,LEN(H27)-5) -> Ambler | K27: =RIGHT(H27,4) -> AK | L27: =LEFT(K27,LEN(K27)-1) -> AK | M27: =SUBSTITUTE(L27,",","") -> AK | N27: =B27 -> 67.1 | O27: =C27 -> 157.85
A28: [ANC] | B28: 61.17 | C28: 150.02 | D28: Anchorage,AK | H28: Anchorage,AK | J28: =LEFT(H28,LEN(H28)-5) -> Anchorage | K28: =RIGHT(H28,4) -> AK | L28: =LEFT(K28,LEN(K28)-1) -> AK | M28: =SUBSTITUTE(L28,",","") -> AK | N28: =B28 -> 61.17 | O28: =C28 -> 150.02
A29: [MRI] | B29: 61.22 | C29: 149.85 | D29: Anchorage,AK | H29: Anchorage,AK | J29: =LEFT(H29,LEN(H29)-5) -> Anchorage | K29: =RIGHT(H29,4) -> AK | L29: =LEFT(K29,LEN(K29)-1) -> AK | M29: =SUBSTITUTE(L29,",","") -> AK | N29: =B29 -> 61.22 | O29: =C29 -> 149.85
A30: [AGN] | B30: 57.83 | C30: 134.97 | D30: Angoon,AK | H30: Angoon,AK | J30: =LEFT(H30,LEN(H30)-5) -> Angoon | K30: =RIGHT(H30,4) -> AK | L30: =LEFT(K30,LEN(K30)-1) -> AK | M30: =SUBSTITUTE(L30,",","") -> AK | N30: =B30 -> 57.83 | O30: =C30 -> 134.97
A31: [ANI] | B31: 61.58 | C31: 159.53 | D31: Aniak,AK | H31: Aniak,AK | J31: =LEFT(H31,LEN(H31)-5) -> Aniak | K31: =RIGHT(H31,4) -> AK | L31: =LEFT(K31,LEN(K31)-1) -> AK | M31: =SUBSTITUTE(L31,",","") -> AK | N31: =B31 -> 61.58 | O31: =C31 -> 159.53
A32: [ANN] | B32: 55.03 | C32: 131.57 | D32: Annette | E32: Isl,AK | H32: Annette Isl,AK | J32: =LEFT(H32,LEN(H32)-5) -> Annette Is | K32: =RIGHT(H32,4) -> ,AK | L32: =LEFT(K32,LEN(K32)-1) -> ,AK | M32: =SUBSTITUTE(L32,",","") -> AK | N32: =B32 -> 55.03 | O32: =C32 -> 131.57
A33: [ATU] | B33: 53.5 | C33: 173.3 | D33: Attu,AK | H33: Attu,AK | J33: =LEFT(H33,LEN(H33)-5) -> Attu | K33: =RIGHT(H33,4) -> AK | L33: =LEFT(K33,LEN(K33)-1) -> AK | M33: =SUBSTITUTE(L33,",","") -> AK | N33: =B33 -> 53.5 | O33: =C33 -> 173.3
A34: [BRW] | B34: 71.3 | C34: 156.78 | D34: Barrow,AK | H34: Barrow,AK | J34: =LEFT(H34,LEN(H34)-5) -> Barrow | K34: =RIGHT(H34,4) -> AK | L34: =LEFT(K34,LEN(K34)-1) -> AK | M34: =SUBSTITUTE(L34,",","") -> AK | N34: =B34 -> 71.3 | O34: =C34 -> 156.78
A35: [BTI] | B35: 70.13 | C35: 143.63 | D35: Barter | E35: Islan,AK | H35: Barter Islan,AK | J35: =LEFT(H35,LEN(H35)-5) -> Barter Isla | K35: =RIGHT(H35,4) -> ,AK | L35: =LEFT(K35,LEN(K35)-1) -> ,AK | M35: =SUBSTITUTE(L35,",","") -> AK | N35: =B35 -> 70.13 | O35: =C35 -> 143.63
A36: [BET] | B36: 60.78 | C36: 161.8 | D36: Bethel | E36: Arpt,AK | H36: Bethel Arpt,AK | J36: =LEFT(H36,LEN(H36)-5) -> Bethel Arp | K36: =RIGHT(H36,4) -> ,AK | L36: =LEFT(K36,LEN(K36)-1) -> ,AK | M36: =SUBSTITUTE(L36,",","") -> AK | N36: =B36 -> 60.78 | O36: =C36 -> 161.8
A37: [BTT] | B37: 66.92 | C37: 151.52 | D37: Bettles,AK | H37: Bettles,AK | J37: =LEFT(H37,LEN(H37)-5) -> Bettles | K37: =RIGHT(H37,4) -> AK | L37: =LEFT(K37,LEN(K37)-1) -> AK | M37: =SUBSTITUTE(L37,",","") -> AK | N37: =B37 -> 66.92 | O37: =C37 -> 151.52
A38: [BIG] | B38: 64 | C38: 145.73 | D38: Big | E38: Delta,AK | H38: Big Delta,AK | J38: =LEFT(H38,LEN(H38)-5) -> Big Delt | K38: =RIGHT(H38,4) -> ,AK | L38: =LEFT(K38,LEN(K38)-1) -> ,AK | M38: =SUBSTITUTE(L38,",","") -> AK | N38: =B38 -> 64 | O38: =C38 -> 145.73
A39: [5BI] | B39: 60.82 | C39: 152.3 | D39: Big | E39: River | F39: Lk,AK | H39: Big River Lk,AK | J39: =LEFT(H39,LEN(H39)-5) -> Big River | K39: =RIGHT(H39,4) -> k,AK | L39: =LEFT(K39,LEN(K39)-1) -> k,A | M39: =SUBSTITUTE(L39,",","") -> kA | N39: =B39 -> 60.82 | O39: =C39 -> 152.3
A40: [Z68] | B40: 63.38 | C40: 148.95 | D40: Cantwell,AK | H40: Cantwell,AK | J40: =LEFT(H40,LEN(H40)-5) -> Cantwell | K40: =RIGHT(H40,4) -> AK | L40: =LEFT(K40,LEN(K40)-1) -> AK | M40: =SUBSTITUTE(L40,",","") -> AK | N40: =B40 -> 63.38 | O40: =C40 -> 148.95
A41: [CDE] | B41: 56 | C41: 134.22 | D41: Cape | E41: Decis,AK | H41: Cape Decis,AK | J41: =LEFT(H41,LEN(H41)-5) -> Cape Deci | K41: =RIGHT(H41,4) -> ,AK | L41: =LEFT(K41,LEN(K41)-1) -> ,AK | M41: =SUBSTITUTE(L41,",","") -> AK | N41: =B41 -> 56 | O41: =C41 -> 134.22
A42: [5HN] | B42: 60.38 | C42: 147.08 | D42: Cape | E42: Hinchi,AK | H42: Cape Hinchi,AK | J42: =LEFT(H42,LEN(H42)-5) -> Cape Hinch | K42: =RIGHT(H42,4) -> ,AK | L42: =LEFT(K42,LEN(K42)-1) -> ,AK | M42: =SUBSTITUTE(L42,",","") -> AK | N42: =B42 -> 60.38 | O42: =C42 -> 147.08
A43: [CSP] | B43: 58.33 | C43: 137.05 | D43: Cape | E43: Spence,AK | H43: Cape Spence,AK | J43: =LEFT(H43,LEN(H43)-5) -> Cape Spenc | K43: =RIGHT(H43,4) -> ,AK | L43: =LEFT(K43,LEN(K43)-1) -> ,AK | M43: =SUBSTITUTE(L43,",","") -> AK | N43: =B43 -> 58.33 | O43: =C43 -> 137.05
A44: [5CE] | B44: 60.33 | C44: 145 | D44: Cape | E44: St | F44: Eli,AK | H44: Cape St Eli,AK | J44: =LEFT(H44,LEN(H44)-5) -> Cape St E | K44: =RIGHT(H44,4) -> i,AK | L44: =LEFT(K44,LEN(K44)-1) -> i,A | M44: =SUBSTITUTE(L44,",","") -> iA | N44: =B44 -> 60.33 | O44: =C44 -> 145
A45: [WCR] | B45: 67.5 | C45: 148.48 | D45: Chandalar | E45: Lk,AK | H45: Chandalar Lk,AK | J45: =LEFT(H45,LEN(H45)-5) -> Chandalar L | K45: =RIGHT(H45,4) -> ,AK | L45: =LEFT(K45,LEN(K45)-1) -> ,AK | M45: =SUBSTITUTE(L45,",","") -> AK | N45: =B45 -> 67.5 | O45: =C45 -> 148.48
A46: [Z00] | B46: 62.88 | C46: 149.83 | D46: Chulitna,AK | H46: Chulitna,AK | J46: =LEFT(H46,LEN(H46)-5) -> Chulitna | K46: =RIGHT(H46,4) -> AK | L46: =LEFT(K46,LEN(K46)-1) -> AK | M46: =SUBSTITUTE(L46,",","") -> AK | N46: =B46 -> 62.88 | O46: =C46 -> 149.83
A47: [CRC] | B47: 65.83 | C47: 144.07 | D47: Circle | E47: City,AK | H47: Circle City,AK | J47: =LEFT(H47,LEN(H47)-5) -> Circle Cit | K47: =RIGHT(H47,4) -> ,AK | L47: =LEFT(K47,LEN(K47)-1) -> ,AK | M47: =SUBSTITUTE(L47,",","") -> AK | N47: =B47 -> 65.83 | O47: =C47 -> 144.07
A48: [CDB] | B48: 55.2 | C48: 162.72 | D48: Cold | E48: Bay,AK | H48: Cold Bay,AK | J48: =LEFT(H48,LEN(H48)-5) -> Cold Ba | K48: =RIGHT(H48,4) -> ,AK | L48: =LEFT(K48,LEN(K48)-1) -> ,AK | M48: =SUBSTITUTE(L48,",","") -> AK | N48: =B48 -> 55.2 | O48: =C48 -> 162.72
A49: [CDV] | B49: 60.5 | C49: 145.5 | D49: Cordova,AK | H49: Cordova,AK | J49: =LEFT(H49,LEN(H49)-5) -> Cordova | K49: =RIGHT(H49,4) -> AK | L49: =LEFT(K49,LEN(K49)-1) -> AK | M49: =SUBSTITUTE(L49,",","") -> AK | N49: =B49 -> 60.5 | O49: =C49 -> 145.5
A50: [CGA] | B50: 55.8 | C50: 133.25 | D50: Craig,AK | H50: Craig,AK | J50: =LEFT(H50,LEN(H50)-5) -> Craig | K50: =RIGHT(H50,4) -> AK | L50: =LEFT(K50,LEN(K50)-1) -> AK | M50: =SUBSTITUTE(L50,",","") -> AK | N50: =B50 -> 55.8 | O50: =C50 -> 133.25
A51: [SCC] | B51: 70.2 | C51: 148.47 | D51: Deadhorse,AK | H51: Deadhorse,AK | J51: =LEFT(H51,LEN(H51)-5) -> Deadhorse | K51: =RIGHT(H51,4) -> AK | L51: =LEFT(K51,LEN(K51)-1) -> AK | M51: =SUBSTITUTE(L51,",","") -> AK | N51: =B51 -> 70.2 | O51: =C51 -> 148.47
A52: [DLG] | B52: 59.05 | C52: 158.52 | D52: Dillingham,AK | H52: Dillingham,AK | J52: =LEFT(H52,LEN(H52)-5) -> Dillingham | K52: =RIGHT(H52,4) -> AK | L52: =LEFT(K52,LEN(K52)-1) -> AK | M52: =SUBSTITUTE(L52,",","") -> AK | N52: =B52 -> 59.05 | O52: =C52 -> 158.52
A53: [5SZ] | B53: 62.73 | C53: 143.92 | D53: Duffys | E53: Tavern,AK | H53: Duffys Tavern,AK | J53: =LEFT(H53,LEN(H53)-5) -> Duffys Taver | K53: =RIGHT(H53,4) -> ,AK | L53: =LEFT(K53,LEN(K53)-1) -> ,AK | M53: =SUBSTITUTE(L53,",","") -> AK | N53: =B53 -> 62.73 | O53: =C53 -> 143.92
A54: [DUT] | B54: 53.88 | C54: 166.53 | D54: Dutch | E54: Harbor,AK | H54: Dutch Harbor,AK | J54: =LEFT(H54,LEN(H54)-5) -> Dutch Harbo | K54: =RIGHT(H54,4) -> ,AK | L54: =LEFT(K54,LEN(K54)-1) -> ,AK | M54: =SUBSTITUTE(L54,",","") -> AK | N54: =B54 -> 53.88 | O54: =C54 -> 166.53
A55: [EAA] | B55: 64.77 | C55: 141.15 | D55: Eagle | E55: Arpt,AK | H55: Eagle Arpt,AK | J55: =LEFT(H55,LEN(H55)-5) -> Eagle Arp | K55: =RIGHT(H55,4) -> ,AK | L55: =LEFT(K55,LEN(K55)-1) -> ,AK | M55: =SUBSTITUTE(L55,",","") -> AK | N55: =B55 -> 64.77 | O55: =C55 -> 141.15
A56: [ERO] | B56: 59.62 | C56: 135.37 | D56: Eldred | E56: Rock,AK | H56: Eldred Rock,AK | J56: =LEFT(H56,LEN(H56)-5) -> Eldred Roc | K56: =RIGHT(H56,4) -> ,AK | L56: =LEFT(K56,LEN(K56)-1) -> ,AK | M56: =SUBSTITUTE(L56,",","") -> AK | N56: =B56 -> 59.62 | O56: =C56 -> 135.37
A57: [ELV] | B57: 58.2 | C57: 136.35 | D57: Elfin | E57: Cove,AK | H57: Elfin Cove,AK | J57: =LEFT(H57,LEN(H57)-5) -> Elfin Cov | K57: =RIGHT(H57,4) -> ,AK | L57: =LEFT(K57,LEN(K57)-1) -> ,AK | M57: =SUBSTITUTE(L57,",","") -> AK | N57: =B57 -> 58.2 | O57: =C57 -> 136.35
A58: [FAI] | B58: 64.82 | C58: 147.87 | D58: Fairbanks,AK | H58: Fairbanks,AK | J58: =LEFT(H58,LEN(H58)-5) -> Fairbanks | K58: =RIGHT(H58,4) -> AK | L58: =LEFT(K58,LEN(K58)-1) -> AK | M58: =SUBSTITUTE(L58,",","") -> AK | N58: =B58 -> 64.82 | O58: =C58 -> 147.87
A59: [FWL] | B59: 62.85 | C59: 154.47 | D59: Farewell,AK | H59: Farewell,AK | J59: =LEFT(H59,LEN(H59)-5) -> Farewell | K59: =RIGHT(H59,4) -> AK | L59: =LEFT(K59,LEN(K59)-1) -> AK | M59: =SUBSTITUTE(L59,",","") -> AK | N59: =B59 -> 62.85 | O59: =C59 -> 154.47
A60: [FIV] | B60: 57.45 | C60: 134.03 | D60: Five | E60: Finger,AK | H60: Five Finger,AK | J60: =LEFT(H60,LEN(H60)-5) -> Five Finge | K60: =RIGHT(H60,4) -> ,AK | L60: =LEFT(K60,LEN(K60)-1) -> ,AK | M60: =SUBSTITUTE(L60,",","") -> AK | N60: =B60 -> 57.45 | O60: =C60 -> 134.03
A61: [FVM] | B61: 65.93 | C61: 149.83 | D61: Five | E61: Mile,AK | H61: Five Mile,AK | J61: =LEFT(H61,LEN(H61)-5) -> Five Mil | K61: =RIGHT(H61,4) -> ,AK | L61: =LEFT(K61,LEN(K61)-1) -> ,AK | M61: =SUBSTITUTE(L61,",","") -> AK | N61: =B61 -> 65.93 | O61: =C61 -> 149.83
A62: [FYU] | B62: 66.57 | C62: 145.27 | D62: Fort | E62: Yukon,AK | H62: Fort Yukon,AK | J62: =LEFT(H62,LEN(H62)-5) -> Fort Yuko | K62: =RIGHT(H62,4) -> ,AK | L62: =LEFT(K62,LEN(K62)-1) -> ,AK | M62: =SUBSTITUTE(L62,",","") -> AK | N62: =B62 -> 66.57 | O62: =C62 -> 145.27
A63: [FNR] | B63: 58.25 | C63: 134.9 | D63: Funter | E63: Bay,AK | H63: Funter Bay,AK | J63: =LEFT(H63,LEN(H63)-5) -> Funter Ba | K63: =RIGHT(H63,4) -> ,AK | L63: =LEFT(K63,LEN(K63)-1) -> ,AK | M63: =SUBSTITUTE(L63,",","") -> AK | N63: =B63 -> 58.25 | O63: =C63 -> 134.9
A64: [GBH] | B64: 68.48 | C64: 149.48 | D64: Galbraith | E64: Lk,AK | H64: Galbraith Lk,AK | J64: =LEFT(H64,LEN(H64)-5) -> Galbraith L | K64: =RIGHT(H64,4) -> ,AK | L64: =LEFT(K64,LEN(K64)-1) -> ,AK | M64: =SUBSTITUTE(L64,",","") -> AK | N64: =B64 -> 68.48 | O64: =C64 -> 149.48
A65: [GAM] | B65: 63.77 | C65: 171.73 | D65: Gambell,AK | H65: Gambell,AK | J65: =LEFT(H65,LEN(H65)-5) -> Gambell | K65: =RIGHT(H65,4) -> AK | L65: =LEFT(K65,LEN(K65)-1) -> AK | M65: =SUBSTITUTE(L65,",","") -> AK | N65: =B65 -> 63.77 | O65: =C65 -> 171.73
A66: [GKN] | B66: 62.15 | C66: 145.45 | D66: Gulkana | E66: Arpt,AK | H66: Gulkana Arpt,AK | J66: =LEFT(H66,LEN(H66)-5) -> Gulkana Arp | K66: =RIGHT(H66,4) -> ,AK | L66: =LEFT(K66,LEN(K66)-1) -> ,AK | M66: =SUBSTITUTE(L66,",","") -> AK | N66: =B66 -> 62.15 | O66: =C66 -> 145.45
A67: [GST] | B67: 58.42 | C67: 135.73 | D67: Gustavus,AK | H67: Gustavus,AK | J67: =LEFT(H67,LEN(H67)-5) -> Gustavus | K67: =RIGHT(H67,4) -> AK | L67: =LEFT(K67,LEN(K67)-1) -> AK | M67: =SUBSTITUTE(L67,",","") -> AK | N67: =B67 -> 58.42 | O67: =C67 -> 135.73
A68: [Z26] | B68: 59.23 | C68: 135.43 | D68: Haines | E68: Hrbor,AK | H68: Haines Hrbor,AK | J68: =LEFT(H68,LEN(H68)-5) -> Haines Hrbo | K68: =RIGHT(H68,4) -> ,AK | L68: =LEFT(K68,LEN(K68)-1) -> ,AK | M68: =SUBSTITUTE(L68,",","") -> AK | N68: =B68 -> 59.23 | O68: =C68 -> 135.43
A69: [5HR] | B69: 61.98 | C69: 152.08 | D69: Hayes | E69: River,AK | H69: Hayes River,AK | J69: =LEFT(H69,LEN(H69)-5) -> Hayes Rive | K69: =RIGHT(H69,4) -> ,AK | L69: =LEFT(K69,LEN(K69)-1) -> ,AK | M69: =SUBSTITUTE(L69,",","") -> AK | N69: =B69 -> 61.98 | O69: =C69 -> 152.08
A70: [5EA] | B70: 63.83 | C70: 149 | D70: Healy | E70: River,AK | H70: Healy River,AK | J70: =LEFT(H70,LEN(H70)-5) -> Healy Rive | K70: =RIGHT(H70,4) -> ,AK | L70: =LEFT(K70,LEN(K70)-1) -> ,AK | M70: =SUBSTITUTE(L70,",","") -> AK | N70: =B70 -> 63.83 | O70: =C70 -> 149
A71: [HOM] | B71: 59.63 | C71: 151.5 | D71: Homer,AK | H71: Homer,AK | J71: =LEFT(H71,LEN(H71)-5) -> Homer | K71: =RIGHT(H71,4) -> AK | L71: =LEFT(K71,LEN(K71)-1) -> AK | M71: =SUBSTITUTE(L71,",","") -> AK | N71: =B71 -> 59.63 | O71: =C71 -> 151.5
A72: [Z49] | B72: 58.1 | C72: 135.45 | D72: Hoonah | E72: Seapl,AK | H72: Hoonah Seapl,AK | J72: =LEFT(H72,LEN(H72)-5) -> Hoonah Seap | K72: =RIGHT(H72,4) -> ,AK | L72: =LEFT(K72,LEN(K72)-1) -> ,AK | M72: =SUBSTITUTE(L72,",","") -> AK | N72: =B72 -> 58.1 | O72: =C72 -> 135.45
A73: [ILI] | B73: 59.75 | C73: 154.92 | D73: Iliamna | E73: Arpt,AK | H73: Iliamna Arpt,AK | J73: =LEFT(H73,LEN(H73)-5) -> Iliamna Arp | K73: =RIGHT(H73,4) -> ,AK | L73: =LEFT(K73,LEN(K73)-1) -> ,AK | M73: =SUBSTITUTE(L73,",","") -> AK | N73: =B73 -> 59.75 | O73: =C73 -> 154.92
A74: [JNU] | B74: 58.37 | C74: 134.58 | D74: Juneau,AK | H74: Juneau,AK | J74: =LEFT(H74,LEN(H74)-5) -> Juneau | K74: =RIGHT(H74,4) -> AK | L74: =LEFT(K74,LEN(K74)-1) -> AK | M74: =SUBSTITUTE(L74,",","") -> AK | N74: =B74 -> 58.37 | O74: =C74 -> 134.58
A75: [KAE] | B75: 56.97 | C75: 133.95 | D75: Kake | E75: Seaplan,AK | H75: Kake Seaplan,AK | J75: =LEFT(H75,LEN(H75)-5) -> Kake Seapla | K75: =RIGHT(H75,4) -> ,AK | L75: =LEFT(K75,LEN(K75)-1) -> ,AK | M75: =SUBSTITUTE(L75,",","") -> AK | N75: =B75 -> 56.97 | O75: =C75 -> 133.95
A76: [ENA] | B76: 60.57 | C76: 151.25 | D76: Kenai,AK | H76: Kenai,AK | J76: =LEFT(H76,LEN(H76)-5) -> Kenai | K76: =RIGHT(H76,4) -> AK | L76: =LEFT(K76,LEN(K76)-1) -> AK | M76: =SUBSTITUTE(L76,",","") -> AK | N76: =B76 -> 60.57 | O76: =C76 -> 151.25
A77: [KTN] | B77: 55.35 | C77: 131.7 | D77: Ketchikan,AK | H77: Ketchikan,AK | J77: =LEFT(H77,LEN(H77)-5) -> Ketchikan | K77: =RIGHT(H77,4) -> AK | L77: =LEFT(K77,LEN(K77)-1) -> AK | M77: =SUBSTITUTE(L77,",","") -> AK | N77: =B77 -> 55.35 | O77: =C77 -> 131.7
A78: [AKN] | B78: 58.68 | C78: 156.65 | D78: King | E78: Salmon,AK | H78: King Salmon,AK | J78: =LEFT(H78,LEN(H78)-5) -> King Salmo | K78: =RIGHT(H78,4) -> ,AK | L78: =LEFT(K78,LEN(K78)-1) -> ,AK | M78: =SUBSTITUTE(L78,",","") -> AK | N78: =B78 -> 58.68 | O78: =C78 -> 156.65
A79: [ADQ] | B79: 57.75 | C79: 152.5 | D79: Kodiak,AK | H79: Kodiak,AK | J79: =LEFT(H79,LEN(H79)-5) -> Kodiak | K79: =RIGHT(H79,4) -> AK | L79: =LEFT(K79,LEN(K79)-1) -> AK | M79: =SUBSTITUTE(L79,",","") -> AK | N79: =B79 -> 57.75 | O79: =C79 -> 152.5
A80: [OTZ] | B80: 66.87 | C80: 162.63 | D80: Kotzebue,AK | H80: Kotzebue,AK | J80: =LEFT(H80,LEN(H80)-5) -> Kotzebue | K80: =RIGHT(H80,4) -> AK | L80: =LEFT(K80,LEN(K80)-1) -> AK | M80: =SUBSTITUTE(L80,",","") -> AK | N80: =B80 -> 66.87 | O80: =C80 -> 162.63
A81: [5WO] | B81: 61.63 | C81: 149.03 | D81: Lazy | E81: Mtn,AK | H81: Lazy Mtn,AK | J81: =LEFT(H81,LEN(H81)-5) -> Lazy Mt | K81: =RIGHT(H81,4) -> ,AK | L81: =LEFT(K81,LEN(K81)-1) -> ,AK | M81: =SUBSTITUTE(L81,",","") -> AK | N81: =B81 -> 61.63 | O81: =C81 -> 149.03
A82: [LNI] | B82: 70.92 | C82: 153.23 | D82: Lonely | E82: (dew),AK | H82: Lonely (dew),AK | J82: =LEFT(H82,LEN(H82)-5) -> Lonely (dew | K82: =RIGHT(H82,4) -> ,AK | L82: =LEFT(K82,LEN(K82)-1) -> ,AK | M82: =SUBSTITUTE(L82,",","") -> AK | N82: =B82 -> 70.92 | O82: =C82 -> 153.23
A83: [MLY] | B83: 65 | C83: 150.65 | D83: Manley | E83: Ht | F83: Sp,AK | H83: Manley Ht Sp,AK | J83: =LEFT(H83,LEN(H83)-5) -> Manley Ht | K83: =RIGHT(H83,4) -> p,AK | L83: =LEFT(K83,LEN(K83)-1) -> p,A | M83: =SUBSTITUTE(L83,",","") -> pA | N83: =B83 -> 65 | O83: =C83 -> 150.65
A84: [MXY] | B84: 61.43 | C84: 142.92 | D84: Mccarthy,AK | H84: Mccarthy,AK | J84: =LEFT(H84,LEN(H84)-5) -> Mccarthy | K84: =RIGHT(H84,4) -> AK | L84: =LEFT(K84,LEN(K84)-1) -> AK | M84: =SUBSTITUTE(L84,",","") -> AK | N84: =B84 -> 61.43 | O84: =C84 -> 142.92
A85: [MCG] | B85: 62.97 | C85: 155.62 | D85: Mcgrath,AK | H85: Mcgrath,AK | J85: =LEFT(H85,LEN(H85)-5) -> Mcgrath | K85: =RIGHT(H85,4) -> AK | L85: =LEFT(K85,LEN(K85)-1) -> AK | M85: =SUBSTITUTE(L85,",","") -> AK | N85: =B85 -> 62.97 | O85: =C85 -> 155.62
A86: [MYU] | B86: 60.37 | C86: 166.27 | D86: Mekoryuk,AK | H86: Mekoryuk,AK | J86: =LEFT(H86,LEN(H86)-5) -> Mekoryuk | K86: =RIGHT(H86,4) -> AK | L86: =LEFT(K86,LEN(K86)-1) -> AK | M86: =SUBSTITUTE(L86,",","") -> AK | N86: =B86 -> 60.37 | O86: =C86 -> 166.27
A87: [MDO] | B87: 59.43 | C87: 146.33 | D87: Middleton | E87: Is,AK | H87: Middleton Is,AK | J87: =LEFT(H87,LEN(H87)-5) -> Middleton I | K87: =RIGHT(H87,4) -> ,AK | L87: =LEFT(K87,LEN(K87)-1) -> ,AK | M87: =SUBSTITUTE(L87,",","") -> AK | N87: =B87 -> 59.43 | O87: =C87 -> 146.33
A88: [MHM] | B88: 63.9 | C88: 152.27 | D88: Minchumina,AK | H88: Minchumina,AK | J88: =LEFT(H88,LEN(H88)-5) -> Minchumina | K88: =RIGHT(H88,4) -> AK | L88: =LEFT(K88,LEN(K88)-1) -> AK | M88: =SUBSTITUTE(L88,",","") -> AK | N88: =B88 -> 63.9 | O88: =C88 -> 152.27
A89: [ENN] | B89: 64.55 | C89: 149.08 | D89: Nenana,AK | H89: Nenana,AK | J89: =LEFT(H89,LEN(H89)-5) -> Nenana | K89: =RIGHT(H89,4) -> AK | L89: =LEFT(K89,LEN(K89)-1) -> AK | M89: =SUBSTITUTE(L89,",","") -> AK | N89: =B89 -> 64.55 | O89: =C89 -> 149.08
A90: [KSM] | B90: 62.07 | C90: 163.3 | D90: New | E90: Andreafs,AK | H90: New Andreafs,AK | J90: =LEFT(H90,LEN(H90)-5) -> New Andreaf | K90: =RIGHT(H90,4) -> ,AK | L90: =LEFT(K90,LEN(K90)-1) -> ,AK | M90: =SUBSTITUTE(L90,",","") -> AK | N90: =B90 -> 62.07 | O90: =C90 -> 163.3
A91: [IKO] | B91: 53.58 | C91: 169.42 | D91: Nikolski,AK | H91: Nikolski,AK | J91: =LEFT(H91,LEN(H91)-5) -> Nikolski | K91: =RIGHT(H91,4) -> AK | L91: =LEFT(K91,LEN(K91)-1) -> AK | M91: =SUBSTITUTE(L91,",","") -> AK | N91: =B91 -> 53.58 | O91: =C91 -> 169.42
A92: [OME] | B92: 64.5 | C92: 165.43 | D92: Nome,AK | H92: Nome,AK | J92: =LEFT(H92,LEN(H92)-5) -> Nome | K92: =RIGHT(H92,4) -> AK | L92: =LEFT(K92,LEN(K92)-1) -> AK | M92: =SUBSTITUTE(L92,",","") -> AK | N92: =B92 -> 64.5 | O92: =C92 -> 165.43
A93: [ORT] | B93: 62.97 | C93: 141.93 | D93: Northway,AK | H93: Northway,AK | J93: =LEFT(H93,LEN(H93)-5) -> Northway | K93: =RIGHT(H93,4) -> AK | L93: =LEFT(K93,LEN(K93)-1) -> AK | M93: =SUBSTITUTE(L93,",","") -> AK | N93: =B93 -> 62.97 | O93: =C93 -> 141.93
A94: [OLI] | B94: 70.5 | C94: 149.88 | D94: Oliktok | E94: Dew,AK | H94: Oliktok Dew,AK | J94: =LEFT(H94,LEN(H94)-5) -> Oliktok De | K94: =RIGHT(H94,4) -> ,AK | L94: =LEFT(K94,LEN(K94)-1) -> ,AK | M94: =SUBSTITUTE(L94,",","") -> AK | N94: =B94 -> 70.5 | O94: =C94 -> 149.88
A95: [PAQ] | B95: 61.6 | C95: 149.08 | D95: Palmer,AK | H95: Palmer,AK | J95: =LEFT(H95,LEN(H95)-5) -> Palmer | K95: =RIGHT(H95,4) -> AK | L95: =LEFT(K95,LEN(K95)-1) -> AK | M95: =SUBSTITUTE(L95,",","") -> AK | N95: =B95 -> 61.6 | O95: =C95 -> 149.08
A96: [5PX] | B96: 63.03 | C96: 145.5 | D96: Paxson,AK | H96: Paxson,AK | J96: =LEFT(H96,LEN(H96)-5) -> Paxson | K96: =RIGHT(H96,4) -> AK | L96: =LEFT(K96,LEN(K96)-1) -> AK | M96: =SUBSTITUTE(L96,",","") -> AK | N96: =B96 -> 63.03 | O96: =C96 -> 145.5
A97: [PSG] | B97: 56.82 | C97: 132.97 | D97: Petersburg,AK | H97: Petersburg,AK | J97: =LEFT(H97,LEN(H97)-5) -> Petersburg | K97: =RIGHT(H97,4) -> AK | L97: =LEFT(K97,LEN(K97)-1) -> AK | M97: =SUBSTITUTE(L97,",","") -> AK | N97: =B97 -> 56.82 | O97: =C97 -> 132.97
A98: [PIZ] | B98: 69.82 | C98: 162.92 | D98: Point | E98: Lay,AK | H98: Point Lay,AK | J98: =LEFT(H98,LEN(H98)-5) -> Point La | K98: =RIGHT(H98,4) -> ,AK | L98: =LEFT(K98,LEN(K98)-1) -> ,AK | M98: =SUBSTITUTE(L98,",","") -> AK | N98: =B98 -> 69.82 | O98: =C98 -> 162.92
A99: [Z76] | B99: 56.25 | C99: 134.65 | D99: Port | E99: Alexndr,AK | H99: Port Alexndr,AK | J99: =LEFT(H99,LEN(H99)-5) -> Port Alexnd | K99: =RIGHT(H99,4) -> ,AK | L99: =LEFT(K99,LEN(K99)-1) -> ,AK | M99: =SUBSTITUTE(L99,",","") -> AK | N99: =B99 -> 56.25 | O99: =C99 -> 134.65
A100: [KPC] | B100: 65.25 | C100: 166.87 | D100: Port | E100: Clarnce,AK | H100: Port Clarnce,AK | J100: =LEFT(H100,LEN(H100)-5) -> Port Clarnc | K100: =RIGHT(H100,4) -> ,AK | L100: =LEFT(K100,LEN(K100)-1) -> ,AK | M100: =SUBSTITUTE(L100,",","") -> AK | N100: =B100 -> 65.25 | O100: =C100 -> 166.87
A101: [PTH] | B101: 56.95 | C101: 158.62 | D101: Port | E101: Heiden,AK | H101: Port Heiden,AK | J101: =LEFT(H101,LEN(H101)-5) -> Port Heide | K101: =RIGHT(H101,4) -> ,AK | L101: =LEFT(K101,LEN(K101)-1) -> ,AK | M101: =SUBSTITUTE(L101,",","") -> AK | N101: =B101 -> 56.95 | O101: =C101 -> 158.62
A102: [PPC] | B102: 66.82 | C102: 150.65 | D102: Prospect | E102: Crk,AK | H102: Prospect Crk,AK | J102: =LEFT(H102,LEN(H102)-5) -> Prospect Cr | K102: =RIGHT(H102,4) -> ,AK | L102: =LEFT(K102,LEN(K102)-1) -> ,AK | M102: =SUBSTITUTE(L102,",","") -> AK | N102: =B102 -> 66.82 | O102: =C102 -> 150.65
A103: [PUO] | B103: 70.25 | C103: 148.33 | D103: Prudhoe | E103: Bay,AK | H103: Prudhoe Bay,AK | J103: =LEFT(H103,LEN(H103)-5) -> Prudhoe Ba | K103: =RIGHT(H103,4) -> ,AK | L103: =LEFT(K103,LEN(K103)-1) -> ,AK | M103: =SUBSTITUTE(L103,",","") -> AK | N103: =B103 -> 70.25 | O103: =C103 -> 148.33
A104: [Z30] | B104: 60.2 | C104: 154.3 | D104: Pt | E104: Alsworth,AK | H104: Pt Alsworth,AK | J104: =LEFT(H104,LEN(H104)-5) -> Pt Alswort | K104: =RIGHT(H104,4) -> ,AK | L104: =LEFT(K104,LEN(K104)-1) -> ,AK | M104: =SUBSTITUTE(L104,",","") -> AK | N104: =B104 -> 60.2 | O104: =C104 -> 154.3
...
